databayes/__init__.py
databayes/etl/__init__.py
databayes/etl/lib_mda.py
databayes/etl/lib_mda_test.py
databayes/modelling/BayesNet.py
databayes/modelling/DiscreteDistribution.py
databayes/modelling/DiscreteVariable.py
databayes/modelling/Potential.py
databayes/modelling/SKlearnClassifiers.py
databayes/modelling/__init__.py
databayes/modelling/core.py
databayes/modelling/features_selection.py
databayes/utils/__init__.py
databayes/utils/data_explorer.py
databayes/utils/etl.py
databayes/utils/ml_performance.py
databayes/utils/ml_performance_comparator.py
databayes/utils/performance_measure.py
databayes-0.0.7.dist-info/LICENCE
databayes-0.0.7.dist-info/METADATA
databayes-0.0.7.dist-info/WHEEL
databayes-0.0.7.dist-info/top_level.txt
databayes-0.0.7.dist-info/RECORD
